odoo/addons/account_fx_spot/README.rst
odoo/addons/account_fx_spot/__init__.py
odoo/addons/account_fx_spot/__manifest__.py
odoo/addons/account_fx_spot/data/account_fx_spot_data.xml
odoo/addons/account_fx_spot/i18n/account_fx_spot.pot
odoo/addons/account_fx_spot/i18n/am.po
odoo/addons/account_fx_spot/i18n/ar.po
odoo/addons/account_fx_spot/i18n/bg.po
odoo/addons/account_fx_spot/i18n/bs.po
odoo/addons/account_fx_spot/i18n/ca.po
odoo/addons/account_fx_spot/i18n/ca_ES.po
odoo/addons/account_fx_spot/i18n/cs.po
odoo/addons/account_fx_spot/i18n/da.po
odoo/addons/account_fx_spot/i18n/de.po
odoo/addons/account_fx_spot/i18n/el_GR.po
odoo/addons/account_fx_spot/i18n/en_GB.po
odoo/addons/account_fx_spot/i18n/es.po
odoo/addons/account_fx_spot/i18n/es_AR.po
odoo/addons/account_fx_spot/i18n/es_CL.po
odoo/addons/account_fx_spot/i18n/es_CO.po
odoo/addons/account_fx_spot/i18n/es_CR.po
odoo/addons/account_fx_spot/i18n/es_DO.po
odoo/addons/account_fx_spot/i18n/es_EC.po
odoo/addons/account_fx_spot/i18n/es_ES.po
odoo/addons/account_fx_spot/i18n/es_MX.po
odoo/addons/account_fx_spot/i18n/es_PE.po
odoo/addons/account_fx_spot/i18n/es_PY.po
odoo/addons/account_fx_spot/i18n/es_VE.po
odoo/addons/account_fx_spot/i18n/et.po
odoo/addons/account_fx_spot/i18n/eu.po
odoo/addons/account_fx_spot/i18n/fa.po
odoo/addons/account_fx_spot/i18n/fi.po
odoo/addons/account_fx_spot/i18n/fr.po
odoo/addons/account_fx_spot/i18n/fr_CA.po
odoo/addons/account_fx_spot/i18n/fr_CH.po
odoo/addons/account_fx_spot/i18n/gl.po
odoo/addons/account_fx_spot/i18n/gl_ES.po
odoo/addons/account_fx_spot/i18n/gu.po
odoo/addons/account_fx_spot/i18n/he.po
odoo/addons/account_fx_spot/i18n/hr.po
odoo/addons/account_fx_spot/i18n/hr_HR.po
odoo/addons/account_fx_spot/i18n/hu.po
odoo/addons/account_fx_spot/i18n/id.po
odoo/addons/account_fx_spot/i18n/it.po
odoo/addons/account_fx_spot/i18n/ja.po
odoo/addons/account_fx_spot/i18n/ko.po
odoo/addons/account_fx_spot/i18n/lt.po
odoo/addons/account_fx_spot/i18n/lt_LT.po
odoo11_addon_account_fx_spot-11.0.1.0.0.99.dev10.dist-info/METADATA
odoo11_addon_account_fx_spot-11.0.1.0.0.99.dev10.dist-info/WHEEL
odoo11_addon_account_fx_spot-11.0.1.0.0.99.dev10.dist-info/top_level.txt
odoo11_addon_account_fx_spot-11.0.1.0.0.99.dev10.dist-info/RECORD
